odoo8_addon_runbot_secure-8.0.1.0.0-py2.7-nspkg.pth
odoo_addons/runbot_secure/runbot_qweb.xml
odoo_addons/runbot_secure/__openerp__.py
odoo_addons/runbot_secure/__init__.py
odoo8_addon_runbot_secure-8.0.1.0.0.dist-info/top_level.txt
odoo8_addon_runbot_secure-8.0.1.0.0.dist-info/WHEEL
odoo8_addon_runbot_secure-8.0.1.0.0.dist-info/RECORD
odoo8_addon_runbot_secure-8.0.1.0.0.dist-info/metadata.json
odoo8_addon_runbot_secure-8.0.1.0.0.dist-info/DESCRIPTION.rst
odoo8_addon_runbot_secure-8.0.1.0.0.dist-info/METADATA
odoo8_addon_runbot_secure-8.0.1.0.0.dist-info/namespace_packages.txt
